ast_nodes/__init__.py
ast_nodes/nodes/__init__.py
ast_nodes/nodes/nodes310.py
ast_nodes/nodes/nodes311.py
ast_nodes/nodes/nodes36.py
ast_nodes/nodes/nodes37.py
ast_nodes/nodes/nodes38.py
ast_nodes/nodes/nodes39.py
ast_nodes/rewriter/__init__.py
ast_nodes/rewriter/rewriter310.py
ast_nodes/rewriter/rewriter311.py
ast_nodes/rewriter/rewriter36.py
ast_nodes/rewriter/rewriter37.py
ast_nodes/rewriter/rewriter38.py
ast_nodes/rewriter/rewriter39.py
ast_nodes-1.0.0.dist-info/LICENSE
ast_nodes-1.0.0.dist-info/METADATA
ast_nodes-1.0.0.dist-info/WHEEL
ast_nodes-1.0.0.dist-info/top_level.txt
ast_nodes-1.0.0.dist-info/RECORD
