Metadata-Version: 2.1
Name: ast-nodes
Version: 1.0.0
Summary: Extensible Python AST nodes
Home-page: https://github.com/tristanlatr/ast-nodes
Author: Various contributors
License: GNU LESSER GENERAL PUBLIC LICENSE Version 2.1
Keywords: static code analysis,python,abstract syntax tree
Platform: UNKNOWN
Requires-Python: >=3.6
Requires-Dist: typing-extensions ; python_version < "3.8"
Provides-Extra: docs
Requires-Dist: pydoctor ; extra == 'docs'
Provides-Extra: test
Requires-Dist: attrs ; extra == 'test'
Requires-Dist: coverage ; extra == 'test'
Requires-Dist: pytest ; extra == 'test'
Requires-Dist: astor ; extra == 'test'
